wiggle/__init__.py
wiggle/_version.py
wiggle/wiggle.py
wiggle-0.1.1.dist-info/licenses/LICENSE
wiggle-0.1.1.dist-info/METADATA
wiggle-0.1.1.dist-info/WHEEL
wiggle-0.1.1.dist-info/top_level.txt
wiggle-0.1.1.dist-info/RECORD
