Metadata-Version: 2.4
Name: wiggle
Version: 0.1.1
Summary: Wiggle Plot for Seismic Data Section
Author-email: gatechzhu <gatechzhu@gmail.com>
License: MIT License
Requires-Python: >=3.10
License-File: LICENSE
Requires-Dist: numpy
Requires-Dist: matplotlib
Dynamic: license-file
